{"errorCode":0,"errorMessage":"","data":[{"mrz_1":"P<AUSHIGGON<<ROWAN<PETER<<<<<<<<<<<<<<<<<<<<","mrz_1_prob":"42.17","mrz_2":"PA72649724AUS6111243M2806262<AE093528<<<<<84","mrz_2_prob":"35.12","passport_number":"PA7264972","passport_number_prob":"35.12","passport_class":"P","passport_class_prob":"87.17","name":"HIGGON ROWAN PETER","name_prob":"42.17","dob":"24/11/1961","dob_prob":"35.12","nationality":"AUSTRALIA","nationality_prob":"35.12","country_code":"AUS","sex":"MALE/M","sex_prob":"35.12","id_number":"AE093528","id_number_prob":"35.12","doe":"26/06/2028","doe_prob":"35.12","poi":"N/A","poi_prob":"N/A","doi":"N/A","doi_prob":"N/A","pob":"N/A","pob_prob":"N/A","overall_score":"35.12","type":"foreign"}]}