{"errorCode":0,"errorMessage":"","data":[{"mrz_1":"P<GBRMONTFORO<<CAROLINE<2OTTIA<<<<<<<<<<<<<<","mrz_1_prob":"51.07","mrz_2":"53685511626BR7810174F2703109<<<<<<<<<<<<<<04","mrz_2_prob":"41.73","passport_number":"536855116","passport_number_prob":"41.73","passport_class":"P","passport_class_prob":"76.07","name":"MONTFORO CAROLINE ZOTTIA","name_prob":"51.07","dob":"17/10/1978","dob_prob":"41.73","nationality":"UNITED KINGDOM OF GREAT BRITAIN AND NORTHERN IRELAND","nationality_prob":"41.73","country_code":"6BR","sex":"FEMALE/F","sex_prob":"41.73","doe":"10/03/2027","doe_prob":"41.73","id_number":"","id_number_prob":"41.73","poi":"N/A","poi_prob":"N/A","doi":"N/A","doi_prob":"N/A","pob":"N/A","pob_prob":"N/A","overall_score":"41.73","type":"foreign"}]}