{"errorCode":0,"errorMessage":"","data":[{"mrz_1":"P<AUSDAHIYABADSHAH<<BHARAT<<<<<<<<<<<<<<<<<<","mrz_1_prob":"83.93","mrz_2":"P479159202AUS8310257M2707060<47895104<<<<<04","mrz_2_prob":"59.74","passport_number":"P47915920","passport_number_prob":"59.74","passport_class":"P","passport_class_prob":"83.93","name":"DAHIYABADSHAH BHARAT","name_prob":"83.93","dob":"25/10/1983","dob_prob":"59.74","nationality":"AUSTRALIA","nationality_prob":"59.74","country_code":"AUS","sex":"MALE/M","sex_prob":"59.74","id_number":"47895104","id_number_prob":"59.74","doe":"06/07/2027","doe_prob":"59.74","poi":"N/A","poi_prob":"N/A","doi":"N/A","doi_prob":"N/A","pob":"N/A","pob_prob":"N/A","overall_score":"59.74","type":"foreign"}]}