{"errorCode":0,"errorMessage":"","data":[{"mrz_1":"PHKORKVAK<<DAEHO<<<<<<<<<<<<<<<<<<<<<<<<<<<<","mrz_1_prob":"37.41","mrz_2":"M698922273<098208190M27122621168019119919910","mrz_2_prob":"47.72","passport_number":"M69892227","passport_number_prob":"47.72","passport_class":"PH","passport_class_prob":"82.41","name":"KVAK DAEHO","name_prob":"37.41","dob":"19/08/1982","dob_prob":"47.72","nationality":"ARUBA","nationality_prob":"47.72","country_code":"09","sex":"MALE/M","sex_prob":"47.72","id_number":"11680191199199","id_number_prob":"47.72","doe":"26/12/2027","doe_prob":"47.72","poi":"N/A","poi_prob":"N/A","doi":"N/A","doi_prob":"N/A","pob":"N/A","pob_prob":"N/A","overall_score":"37.41","type":"foreign"}]}