{"errorCode":0,"errorMessage":"","data":[{"mrz_1":"P<USAYANG<<TONY<SHUI<KUAN<<<<<<<<<<<<<<<<<<<","mrz_1_prob":"50.77","mrz_2":"54583473980545301090M2607252183107450<165500","mrz_2_prob":"52.69","passport_number":"545834739","passport_number_prob":"52.69","passport_class":"P","passport_class_prob":"75.77","name":"YANG TONY SHUI KUAN","name_prob":"50.77","dob":"09/01/1953","dob_prob":"52.69","nationality":"ARUBA","nationality_prob":"52.69","country_code":"054","sex":"MALE/M","sex_prob":"52.69","id_number":"183107450 1655","id_number_prob":"52.69","doe":"25/07/2026","doe_prob":"52.69","poi":"N/A","poi_prob":"N/A","doi":"N/A","doi_prob":"N/A","pob":"N/A","pob_prob":"N/A","overall_score":"50.77","type":"foreign"}]}