{"errorCode":0,"errorMessage":"","data":[{"mrz_1":"P<TNNYANG<<JEN<HUNG<<<<<<<<<<<<<<<<<<<<<<<<<","mrz_1_prob":"36.92","mrz_2":"B1528904197NN7802018M2706270112256448<<<<<62","mrz_2_prob":"25.44","passport_number":"B15289041","passport_number_prob":"25.44","passport_class":"P","passport_class_prob":"81.92","name":"YANG JEN HUNG","name_prob":"36.92","dob":"01/02/1978","dob_prob":"25.44","nationality":"ANDORRA","nationality_prob":"25.44","country_code":"7NN","sex":"MALE/M","sex_prob":"25.44","id_number":"112256448","id_number_prob":"25.44","doe":"27/06/2027","doe_prob":"25.44","poi":"N/A","poi_prob":"N/A","doi":"N/A","doi_prob":"N/A","pob":"N/A","pob_prob":"N/A","overall_score":"25.44","type":"foreign"}]}