{"errorCode":0,"errorMessage":"","data":[{"mrz_1":"P<KORSONG<<HYUNGMIN<<<<<<<<<<<<<<<<<<<<<<<<<","mrz_1_prob":"59.03","mrz_2":"M440099840K087202124M25031701621915112076880","mrz_2_prob":"35.10","passport_number":"M44009984","passport_number_prob":"35.10","passport_class":"P","passport_class_prob":"84.03","name":"SONG HYUNGMIN","name_prob":"59.03","dob":"12/02/1972","dob_prob":"35.10","nationality":"KAZAKHSTAN","nationality_prob":"35.10","country_code":"K08","sex":"MALE/M","sex_prob":"35.10","id_number":"16219151120768","id_number_prob":"35.10","doe":"17/03/2025","doe_prob":"35.10","poi":"N/A","poi_prob":"N/A","doi":"N/A","doi_prob":"N/A","pob":"N/A","pob_prob":"N/A","overall_score":"35.10","type":"foreign"}]}