{"errorCode":0,"errorMessage":"","data":[{"mrz_1":"P<KORCHA<<SEUNGYEE<<<<<<<<<<<<<<<<<<<<<<<<<<","mrz_1_prob":"75.23","mrz_2":"M940399431K0M9205060F27080232055016V17843540","mrz_2_prob":"21.25","passport_number":"M94039943","passport_number_prob":"21.25","passport_class":"P","passport_class_prob":"75.23","name":"CHA SEUNGYEE","name_prob":"75.23","dob":"06/05/1992","dob_prob":"21.25","nationality":"CAMBODIA","nationality_prob":"21.25","country_code":"K0M","sex":"FEMALE/F","sex_prob":"21.25","id_number":"2055016V178435","id_number_prob":"21.25","doe":"02/08/2027","doe_prob":"21.25","poi":"N/A","poi_prob":"N/A","doi":"N/A","doi_prob":"N/A","pob":"N/A","pob_prob":"N/A","overall_score":"21.25","type":"foreign"}]}