{"errorCode":0,"errorMessage":"","data":[{"mrz_1":"PMKORKWAK<<DONG<KYOUNG<<<<<<<<","mrz_1_prob":"66.99","mrz_2":"M821065525K0R7207060M270718519056","mrz_2_prob":"40.60","passport_number":"M82106552","passport_number_prob":"40.60","passport_class":"PM","passport_class_prob":"91.99","name":"KWAK DONG KYOUNG","name_prob":"66.99","dob":"06/07/1972","dob_prob":"40.60","nationality":"KIRIBATI","nationality_prob":"40.60","country_code":"K0R","sex":"MALE/M","sex_prob":"40.60","doe":"18/07/2027","doe_prob":"40.60","id_number":"","id_number_prob":"","poi":"N/A","poi_prob":"N/A","doi":"N/A","doi_prob":"N/A","pob":"N/A","pob_prob":"N/A","overall_score":"40.60","type":"foreign"}]}