{"errorCode":0,"errorMessage":"","data":[{"mrz_1":"P<INDNEVE<<SHAPHIL<NARAYAN<<<<<<<<<<<<<<<<<<","mrz_1_prob":"49.55","mrz_2":"C3271082<0INN8007016M2507260<<<<<<<<<<<<<<<6","mrz_2_prob":"29.96","passport_number":"C3271082","passport_number_prob":"29.96","passport_class":"P","passport_class_prob":"94.55","name":"NEVE SHAPHIL NARAYAN","name_prob":"49.55","dob":"01/07/1980","dob_prob":"29.96","nationality":"INDONESIA","nationality_prob":"29.96","country_code":"INN","sex":"MALE/M","sex_prob":"29.96","doe":"26/07/2025","doe_prob":"29.96","id_number":"","id_number_prob":"29.96","poi":"N/A","poi_prob":"N/A","doi":"N/A","doi_prob":"N/A","pob":"N/A","pob_prob":"N/A","overall_score":"29.96","type":"foreign"}]}