{"errorCode":0,"errorMessage":"","data":[{"mrz_1":"P<USAHUNG<<TUNG<VAN<<<<<<<<<<<<<<<<<<<<<<<<<","mrz_1_prob":"87.29","mrz_2":"578736329405A5901205M2707118419998733<865888","mrz_2_prob":"58.74","passport_number":"578736329","passport_number_prob":"58.74","passport_class":"P","passport_class_prob":"87.29","name":"HUNG TUNG VAN","name_prob":"87.29","dob":"20/01/1959","dob_prob":"58.74","nationality":"ANGUILLA","nationality_prob":"58.74","country_code":"05A","sex":"MALE/M","sex_prob":"58.74","id_number":"419998733 8658","id_number_prob":"58.74","doe":"11/07/2027","doe_prob":"58.74","poi":"N/A","poi_prob":"N/A","doi":"N/A","doi_prob":"N/A","pob":"N/A","pob_prob":"N/A","overall_score":"58.74","type":"foreign"}]}