{"errorCode":0,"errorMessage":"","data":[{"mrz_1":"P<USAKESSLER<<ALAN<GARY<<<<<<<<<<<<<<<<<<<","mrz_1_prob":"49.03","mrz_2":"4965135661USA5712023M2211053253392801<<<<","mrz_2_prob":"38.61","passport_number":"496513566","passport_number_prob":"38.61","passport_class":"P","passport_class_prob":"94.03","name":"KESSLER ALAN GARY","name_prob":"49.03","dob":"02/12/1957","dob_prob":"38.61","nationality":"UNITED STATES OF AMERICA","nationality_prob":"38.61","country_code":"USA","sex":"MALE/M","sex_prob":"38.61","doe":"05/11/2022","doe_prob":"38.61","id_number":"","id_number_prob":"","poi":"N/A","poi_prob":"N/A","doi":"N/A","doi_prob":"N/A","pob":"N/A","pob_prob":"N/A","overall_score":"38.61","type":"foreign"}]}