{"errorCode":0,"errorMessage":"","data":[{"mrz_1":"P<KORSHIN<<YE<EUN<<<<<<<<<<<<<<<<<<<<<<<<<<<","mrz_1_prob":"48.98","mrz_2":"M491031600K0R9610183F25051522179718V16480014","mrz_2_prob":"58.70","passport_number":"M49103160","passport_number_prob":"58.70","passport_class":"P","passport_class_prob":"93.98","name":"SHIN YE EUN","name_prob":"48.98","dob":"18/10/1996","dob_prob":"58.70","nationality":"KIRIBATI","nationality_prob":"58.70","country_code":"K0R","sex":"FEMALE/F","sex_prob":"58.70","id_number":"2179718V164800","id_number_prob":"58.70","doe":"15/05/2025","doe_prob":"58.70","poi":"N/A","poi_prob":"N/A","doi":"N/A","doi_prob":"N/A","pob":"N/A","pob_prob":"N/A","overall_score":"48.98","type":"foreign"}]}